tasauria/__init__.py
tasauria/client.py
tasauria/exceptions.py
tasauria/types.py
tasauria/adapters/__init__.py
tasauria/adapters/async_.py
tasauria/commands/__init__.py
tasauria/commands/client.py
tasauria/commands/joypad.py
tasauria/commands/memory.py
tasauria/commands/meta.py
tasauria/commands/movie.py
tasauria/commands/savestate.py
tasauria/systems/__init__.py
tasauria/systems/amiga.py
tasauria/systems/atari_2600.py
tasauria/systems/atari_7800.py
tasauria/systems/atari_lynx.py
tasauria/systems/c64.py
tasauria/systems/colecovision.py
tasauria/systems/gb.py
tasauria/systems/gba.py
tasauria/systems/genesis.py
tasauria/systems/intellivision.py
tasauria/systems/master_system.py
tasauria/systems/n3ds.py
tasauria/systems/n64.py
tasauria/systems/nds.py
tasauria/systems/nes.py
tasauria/systems/ngp.py
tasauria/systems/odyssey2.py
tasauria/systems/pcfx.py
tasauria/systems/psx.py
tasauria/systems/saturn.py
tasauria/systems/snes.py
tasauria/systems/turbografx.py
tasauria/systems/vectrex.py
tasauria/systems/virtual_boy.py
tasauria/systems/zx_spectrum.py
tasauria-1.0.5.dist-info/licenses/LICENSE
tasauria-1.0.5.dist-info/METADATA
tasauria-1.0.5.dist-info/WHEEL
tasauria-1.0.5.dist-info/top_level.txt
tasauria-1.0.5.dist-info/RECORD
