Metadata-Version: 2.4
Name: tasauria
Version: 1.0.5
Summary: A library for remotely controlling BizHawk with custom scripts
Author: scarletcafe
License: The MIT License (MIT)
Project-URL: Issue tracker, https://github.com/scarletcafe/tasauria/issues
Classifier: Development Status :: 3 - Alpha
Classifier: Intended Audience :: Developers
Classifier: License :: OSI Approved :: MIT License
Classifier: Natural Language :: English
Classifier: Operating System :: OS Independent
Classifier: Programming Language :: Python :: 3 :: Only
Classifier: Programming Language :: Python :: 3.9
Classifier: Programming Language :: Python :: 3.10
Classifier: Programming Language :: Python :: 3.11
Classifier: Programming Language :: Python :: 3.12
Classifier: Programming Language :: Python :: 3.13
Classifier: Programming Language :: Python :: 3.14
Classifier: Topic :: Games/Entertainment
Classifier: Topic :: Internet
Classifier: Topic :: Software Development :: Libraries
Classifier: Topic :: Software Development :: Libraries :: Python Modules
Classifier: Topic :: System :: Emulators
Classifier: Typing :: Typed
Requires-Python: >=3.9
License-File: LICENSE
Requires-Dist: aiohttp<4,>=3.11
Requires-Dist: click<9,>=8.1
Provides-Extra: lint
Requires-Dist: ruff<1.0,>=0.13; extra == "lint"
Provides-Extra: documentation
Requires-Dist: lxml<7.0,>=6.0; extra == "documentation"
Dynamic: license-file
